<?xml version="1.0" encoding="UTF-8"?>
<objects serializationModel="Studio.02.02.00">
	<object class="AudioFile" id="{ad241d50-502f-4b0e-bdc3-698616379216}">
		<property name="assetPath">
			<value>SFX/Towers/Tower Builds/Tower_Slide_v2_1.wav</value>
		</property>
		<property name="frequencyInKHz">
			<value>48</value>
		</property>
		<property name="channelCount">
			<value>2</value>
		</property>
		<property name="length">
			<value>2</value>
		</property>
		<relationship name="masterAssetFolder">
			<destination>{57242b32-9511-4dfb-ad60-d2ea84eee8bf}</destination>
		</relationship>
	</object>
</objects>
